FA module/FullAdderBehavior.v
module full_adder_behave(IN1, IN2, Carry_In, Sum, Carry_Out);
	input IN1, IN2, Carry_In;
	output Sum, Carry_Out;
	
	wire sum_not_and_input[3:0], carry_not_and_input[2:0];
	
	assign sum_not_and_input[0]=~(IN1&IN2&Carry_In);
	assign sum_not_and_input[1]=~(IN1&~IN2&~Carry_In);	
	assign sum_not_and_input[2]=~(~IN1&IN2&~Carry_In);
	assign sum_not_and_input[3]=~(~IN1&~IN2&Carry_In);
	
	assign carry_not_and_input[0]=~(IN1&IN2);
	assign carry_not_and_input[1]=~(IN1&Carry_In);
	assign carry_not_and_input[2]=~(IN2&Carry_In);
	
	assign Sum=~(sum_not_and_input[0]&sum_not_and_input[1]&sum_not_and_input[2]& sum_not_and_input[3]);
	assign Carry_Out=~(carry_not_and_input[0]&carry_not_and_input[1]&carry_not_and_input[2]);
	
endmodule

test module/TestBehave.v
module test;
	reg a, b, carry_in;
	wire behave_sum, behave_carry_out;
	
	full_adder_behave FA1(a, b, carry_in, behave_sum, behave_carry_out);
	
	initial begin
	
		a=1'b0;b=1'b0;carry_in=1'b0;
	#1	a=1'b0;b=1'b0;carry_in=1'b1;
	#1	a=1'b0;b=1'b1;carry_in=1'b0;
	#1	a=1'b0;b=1'b1;carry_in=1'b1;
	#1	a=1'b1;b=1'b0;carry_in=1'b0;
	#1	a=1'b1;b=1'b0;carry_in=1'b1;
	#1	a=1'b1;b=1'b1;carry_in=1'b0;
	#1	a=1'b1;b=1'b1;carry_in=1'b1;
	#1;
	
	end
	
	initial begin	
	$monitor("Behavioral Input1:%b, Input2:%b, Input3:%b, Sum:%b, carry_out:%b", a, b, carry_in, behave_sum, behave_carry_out);	
	end
	
	initial begin
	
	$dumpfile("TestBehave.vcd");
	$dumpvars;
	
	end
	
endmodule

vcd output/TestBehave.vcd
$date
	Tue Mar 27 14:55:51 2018
$end
$version
	Icarus Verilog
$end
$timescale
	1s
$end
$scope module test $end
$var wire 1 ! behave_sum $end
$var wire 1 " behave_carry_out $end
$var reg 1 # a $end
$var reg 1 $ b $end
$var reg 1 % carry_in $end
$scope module FA1 $end
$var wire 1 % Carry_In $end
$var wire 1 " Carry_Out $end
$var wire 1 # IN1 $end
$var wire 1 $ IN2 $end
$var wire 1 ! Sum $end
$upscope $end
$upscope $end
$enddefinitions $end
#0
$dumpvars
0%
0$
0#
0"
0!
$end
#1
1!
1%
#2
1!
0%
1$
#3
0!
1"
1%
#4
1!
0"
0%
0$
1#
#5
0!
1"
1%
#6
0%
1$
#7
1!
1%
