FA module/FullAdderStructural.v
module full_adder_struct(IN1, IN2, Carry_In, Sum, Carry_Out);
	input IN1, IN2, Carry_In;
	output Sum, Carry_Out;
	
	wire in[2:0], not_in[2:0], sum_not_and_input[3:0], carry_not_and_input[2:0];
	
	assign in[0]=IN1;
	assign in[1]=IN2;
	assign in[2]=Carry_In;
	
	not not1(not_in[0], in[0]);
	not not2(not_in[1], in[1]);
	not not3(not_in[2], in[2]);
	
	nand nand1(sum_not_and_input[0], in[0], in[1], in[2]);
	nand nand2(sum_not_and_input[1], in[0], not_in[1], not_in[2]);
	nand nand3(sum_not_and_input[2], not_in[0], in[1], not_in[2]);
	nand nand4(sum_not_and_input[3], not_in[0], not_in[1], in[2]);
	
	
	nand nand5(carry_not_and_input[0], in[0], in[1]);
	nand nand6(carry_not_and_input[1], in[0], in[2]);
	nand nand7(carry_not_and_input[2], in[1], in[2]);
	
	nand nand8(Sum, sum_not_and_input[0], sum_not_and_input[1], sum_not_and_input[2], sum_not_and_input[3]);
	nand nand9(Carry_Out, carry_not_and_input[0], carry_not_and_input[1], carry_not_and_input[2]);
	
endmodule

test module/TestStruct.v
module test;
	reg a, b, carry_in;
	wire struct_sum, struct_carry_out;
	
	full_adder_struct FA1(a, b, carry_in, struct_sum, struct_carry_out);
	
	initial begin
	
		a=1'b0;b=1'b0;carry_in=1'b0;
	#1	a=1'b0;b=1'b0;carry_in=1'b1;
	#1	a=1'b0;b=1'b1;carry_in=1'b0;
	#1	a=1'b0;b=1'b1;carry_in=1'b1;
	#1	a=1'b1;b=1'b0;carry_in=1'b0;
	#1	a=1'b1;b=1'b0;carry_in=1'b1;
	#1	a=1'b1;b=1'b1;carry_in=1'b0;
	#1	a=1'b1;b=1'b1;carry_in=1'b1;
	#1;
	
	end
	
	initial begin	
	$monitor("Structural Input1:%b, Input2:%b, Input3:%b, Sum:%b, carry_out:%b", a, b, carry_in, struct_sum, struct_carry_out);	
	end
	
	initial begin
	
	$dumpfile("TestStruct.vcd");
	$dumpvars;
	
	end
	
endmodule

vcd output/TestStruct.vcd
$date
	Tue Mar 27 14:56:37 2018
$end
$version
	Icarus Verilog
$end
$timescale
	1s
$end
$scope module test $end
$var wire 1 ! struct_sum $end
$var wire 1 " struct_carry_out $end
$var reg 1 # a $end
$var reg 1 $ b $end
$var reg 1 % carry_in $end
$scope module FA1 $end
$var wire 1 % Carry_In $end
$var wire 1 " Carry_Out $end
$var wire 1 # IN1 $end
$var wire 1 $ IN2 $end
$var wire 1 ! Sum $end
$upscope $end
$upscope $end
$enddefinitions $end
#0
$dumpvars
0%
0$
0#
0"
0!
$end
#1
1!
1%
#2
1!
0%
1$
#3
0!
1"
1%
#4
1!
0"
0%
0$
1#
#5
0!
1"
1%
#6
0%
1$
#7
1!
1%
